basicdsplibrary/__init__.py
basicdsplibrary-0.0.12.dist-info/licenses/LICENCE.txt
basicdsplibrary-0.0.12.dist-info/METADATA
basicdsplibrary-0.0.12.dist-info/WHEEL
basicdsplibrary-0.0.12.dist-info/top_level.txt
basicdsplibrary-0.0.12.dist-info/RECORD
