Metadata-Version: 2.4
Name: basicdsplibrary
Version: 0.0.12
Summary: Basic DSP library without numpy
Home-page: https://github.com/shivarao101/vcet-dsp-bec502
Author: Shivaprasad
Author-email: shivarao101@gmail.com
License: MIT
Keywords: DFT,IDFT,DFS,DTFT,DCT,DWT,Radix-2 DIT & DIF,Overlap save and add
Classifier: Development Status :: 3 - Alpha
Classifier: Environment :: Console
Classifier: Intended Audience :: Education
Classifier: License :: OSI Approved :: MIT License
Classifier: Natural Language :: English
Classifier: Operating System :: OS Independent
Classifier: Programming Language :: Python
Classifier: Topic :: Scientific/Engineering
License-File: LICENCE.txt
Dynamic: author
Dynamic: author-email
Dynamic: classifier
Dynamic: description
Dynamic: description-content-type
Dynamic: home-page
Dynamic: keywords
Dynamic: license
Dynamic: license-file
Dynamic: summary
